mnemonic/__init__.py
mnemonic/mnemonic.py
mnemonic/secretsharing.py
mnemonic/wordlist/chinese_simplified.txt
mnemonic/wordlist/chinese_traditional.txt
mnemonic/wordlist/english.txt
mnemonic/wordlist/french.txt
mnemonic/wordlist/italian.txt
mnemonic/wordlist/japanese.txt
mnemonic/wordlist/korean.txt
mnemonic/wordlist/spanish.txt
mnemonic_ceres-0.19a0.dist-info/METADATA
mnemonic_ceres-0.19a0.dist-info/RECORD
mnemonic_ceres-0.19a0.dist-info/WHEEL
mnemonic_ceres-0.19a0.dist-info/top_level.txt
