Metadata-Version: 2.1
Name: mnemonic-ceres
Version: 0.19a0
Summary: Implementation of Bitcoin BIP-0039
Home-page: https://github.com/PetersonZhao/python-mnemonic
Author: Bitcoin TREZOR
Author-email: zhao6217@gmail.com
License: UNKNOWN
Platform: UNKNOWN
Classifier: License :: OSI Approved :: MIT License
Classifier: Operating System :: POSIX :: Linux
Classifier: Operating System :: Microsoft :: Windows
Classifier: Operating System :: MacOS :: MacOS X
Requires-Dist: pbkdf2
